django_oscar_telegram_bot-0.5.0.dist-info/DESCRIPTION.rst
django_oscar_telegram_bot-0.5.0.dist-info/METADATA
django_oscar_telegram_bot-0.5.0.dist-info/RECORD
django_oscar_telegram_bot-0.5.0.dist-info/WHEEL
django_oscar_telegram_bot-0.5.0.dist-info/metadata.json
django_oscar_telegram_bot-0.5.0.dist-info/top_level.txt
oscar_telegrambot/__init__.py
oscar_telegrambot/commands_views.py
oscar_telegrambot/handlers.py
oscar_telegrambot/models.py
oscar_telegrambot/templates/oscar_telegrambot/messages/command_categories_detail_keyboard.txt
oscar_telegrambot/templates/oscar_telegrambot/messages/command_categories_detail_text.txt
oscar_telegrambot/templates/oscar_telegrambot/messages/command_categories_list_keyboard.txt
oscar_telegrambot/templates/oscar_telegrambot/messages/command_categories_list_text.txt
oscar_telegrambot/templates/oscar_telegrambot/messages/command_help_text.txt
oscar_telegrambot/templates/oscar_telegrambot/messages/command_orders_detail_text.txt
oscar_telegrambot/templates/oscar_telegrambot/messages/command_orders_list_keyboard.txt
oscar_telegrambot/templates/oscar_telegrambot/messages/command_orders_list_text.txt
oscar_telegrambot/templates/oscar_telegrambot/messages/command_products_detail_text.txt
oscar_telegrambot/templates/oscar_telegrambot/messages/command_products_list_keyboard.txt
oscar_telegrambot/templates/oscar_telegrambot/messages/command_products_list_text.txt
oscar_telegrambot/templates/oscar_telegrambot/messages/command_start_text.txt
oscar_telegrambot/templates/oscar_telegrambot/messages/command_unknown_text.txt
oscar_telegrambot/templatetags/__init__.py
oscar_telegrambot/templatetags/telegrambot_tags.py
