Metadata-Version: 2.0
Name: django-oscar-telegram-bot
Version: 0.5.0
Summary: Telegram Bot for Oscar shops
Home-page: https://github.com/jlmadurga/django-oscar-telegram-bot
Author: Juan Madurga
Author-email: jlmadurga@gmail.com
License: BSD
Keywords: django-oscar-telegram-bot
Platform: UNKNOWN
Classifier: Development Status :: 3 - Alpha
Classifier: Framework :: Django
Classifier: Framework :: Django :: 1.8
Classifier: Intended Audience :: Developers
Classifier: License :: OSI Approved :: BSD License
Classifier: Natural Language :: English
Classifier: Programming Language :: Python :: 2
Classifier: Programming Language :: Python :: 2.7
Classifier: Programming Language :: Python :: 3
Classifier: Programming Language :: Python :: 3.4
Classifier: Programming Language :: Python :: 3.5
Requires-Dist: django-oscar (==1.1.1)
Requires-Dist: django-telegram-bot (==0.5.0)
